SQLite3_0611/__init__.py
SQLite3_0611/api.py
SQLite3_0611-0.0.1.dist-info/LICENSE
SQLite3_0611-0.0.1.dist-info/METADATA
SQLite3_0611-0.0.1.dist-info/WHEEL
SQLite3_0611-0.0.1.dist-info/top_level.txt
SQLite3_0611-0.0.1.dist-info/RECORD
